{
  "ascendant": "Virgo",
  "planet": "Venus",
  "house": 11,
  "lang": "EN",
  "title": "Venus in 11th House for Virgo Ascendant",
  "summary": "When Venus transits the 11th house for Virgo Ascendant, it activates gains, networks, friendships, and fulfillment of desires. This period supports financial improvement through social connections, collaborations, and community involvement. Friends and allies become supportive, and long-term goals gain momentum through cooperation. Creative or relationship-driven opportunities bring tangible benefits. Social popularity increases, but expectations should remain realistic. This transit favors steady gains, value-aligned networking, and balanced enjoyment of social life without overdependence on approval.",
  "sections": [
    {
      "heading": "Core Personality",
      "points": [
        "Friendly and cooperative attitude strengthens",
        "Desire for shared success increases",
        "Values align with group harmony",
        "Optimism toward future goals grows"
      ]
    },
    {
      "heading": "Career & Direction",
      "points": [
        "Gains through teamwork and alliances",
        "Networking opens new opportunities",
        "Support from colleagues and seniors",
        "Goals progress through collaboration"
      ]
    },
    {
      "heading": "Relationships",
      "points": [
        "Friendships become supportive",
        "Romance may arise from social circles",
        "Mutual respect within groups",
        "Reduced conflicts through diplomacy"
      ]
    },
    {
      "heading": "Finance & Growth",
      "points": [
        "Steady financial gains",
        "Income via networks or referrals",
        "Benefits from long-term plans",
        "Avoid excessive social spending"
      ]
    },
    {
      "heading": "Health & Mindset",
      "points": [
        "Positive mood from social support",
        "Stress reduces through companionship",
        "Risk of over-socializing",
        "Need to balance pleasure and rest"
      ]
    }
  ],
  "strengths": [
    "Strong networks",
    "Financial gains",
    "Collaborative success",
    "Social harmony",
    "Goal fulfillment"
  ],
  "challenges": [
    "Overreliance on friends",
    "Unrealistic expectations",
    "Social distractions",
    "Peer pressure spending",
    "Approval-seeking"
  ],
  "closing": "Venus in the 11th house brings gains and social support to Virgo Ascendant, rewarding balanced networking and value-driven goals.",
  "cta_context": {
    "type": "transit",
    "ascendant": "Virgo",
    "planet": "Venus",
    "house": 11
  }
}
