{
  "ascendant": "Cancer",
  "planet": "Mars",
  "house": 7,
  "lang": "en",
  "title": "Mars Transit in the 7th House for Cancer Ascendant",
  "summary": "Mars transiting the seventh house activates partnerships, contracts, and one-to-one dynamics. For Cancer ascendants, this phase brings intensity into relationships, making interactions more assertive and outcome-focused. You may feel compelled to take the lead in collaborations or confront unresolved issues directly. While passion and drive can strengthen bonds and business dealings, impatience or dominance can trigger conflicts. This transit favors decisive negotiations and energetic partnerships, provided you balance assertiveness with cooperation and respect mutual boundaries.",
  "sections": [
    {
      "heading": "Core Personality",
      "points": [
        "Stronger assertiveness in dealings with others",
        "Heightened desire to lead partnerships",
        "Clear focus on results in interactions",
        "Need to manage confrontational tendencies"
      ]
    },
    {
      "heading": "Career",
      "points": [
        "Active negotiations and client-facing roles",
        "Good time for partnerships and contracts",
        "Results through decisive action",
        "Avoid power struggles with associates"
      ]
    },
    {
      "heading": "Relationships",
      "points": [
        "Increased passion and intensity",
        "Possibility of arguments due to dominance",
        "Direct handling of unresolved issues",
        "Mutual respect maintains harmony"
      ]
    },
    {
      "heading": "Finance",
      "points": [
        "Financial outcomes linked to partnerships",
        "Decisive moves in joint ventures",
        "Shared expenses may rise",
        "Clarity in agreements is essential"
      ]
    },
    {
      "heading": "Mental / Inner",
      "points": [
        "Strong urge to prove oneself through others",
        "Restlessness in close interactions",
        "Quick emotional reactions",
        "Conscious restraint brings balance"
      ]
    }
  ],
  "strengths": [
    "Decisive partnership approach",
    "Courage to address conflicts",
    "Energetic collaboration",
    "Strong negotiation drive"
  ],
  "challenges": [
    "Relationship conflicts",
    "Dominance and impatience",
    "Power struggles",
    "Emotional reactivity"
  ],
  "closing": "This transit tests strength through cooperation.\nUse Mars to resolve, not escalate, differences.\nBalanced assertiveness builds lasting alliances.",
  "cta_context": {
    "type": "transit",
    "ascendant": "Cancer",
    "planet": "Mars",
    "house": 7
  }
}
