{
  "ascendant": "Capricorn",
  "planet": "Mercury",
  "house": 8,
  "lang": "HI",
  "title": "मकर लग्न के लिए अष्टम भाव में बुध का गोचर",
  "summary": "मकर लग्न के लिए बुध का अष्टम भाव में गोचर सोच को गहराई, शोध और रणनीति की ओर ले जाता है। छिपे विषयों, साझा धन, कर और भावनात्मक जटिलताओं पर विचार बढ़ता है। विश्वास और गोपनीयता से जुड़े संवाद सक्रिय होते हैं। यह समय विश्लेषण, ऑडिट और पर्दे के पीछे समस्या-समाधान के लिए अनुकूल है। हालांकि अधिक सोच शंका और तनाव बढ़ा सकती है। विवेकपूर्ण सोच से परिवर्तन सहज बनता है।",
  "sections": [
    {
      "title": "मूल व्यक्तित्व",
      "points": [
        "गहन और खोजी सोच",
        "छिपे सत्य में रुचि",
        "रणनीतिक बुद्धि",
        "शंका का जोखिम"
      ]
    },
    {
      "title": "करियर",
      "points": [
        "शोध और विश्लेषण अनुकूल",
        "गोपनीय कार्यों में महत्व",
        "जटिल मामलों का समाधान",
        "अति-प्रश्न से बचें"
      ]
    },
    {
      "title": "रिश्ते",
      "points": [
        "विश्वास पर गहन संवाद",
        "ईमानदार बातचीत आवश्यक",
        "मानसिक जांच से असहजता",
        "स्पष्टता से संतुलन"
      ]
    },
    {
      "title": "वित्त",
      "points": [
        "साझा संपत्ति और कर पर ध्यान",
        "ऑडिट और समीक्षा अनुकूल",
        "छिपे खर्च सामने आते हैं",
        "योजना से हानि से बचाव"
      ]
    },
    {
      "title": "मानसिक / आंतरिक",
      "points": [
        "तीव्र विचार प्रवाह",
        "गहरे अर्थ की जिज्ञासा",
        "अति-विश्लेषण से चिंता",
        "संरचित सोच से शांति"
      ]
    }
  ],
  "strengths": [
    "शोध क्षमता",
    "रणनीतिक गहराई",
    "विश्लेषणात्मक साहस",
    "समस्या-समाधान स्पष्टता"
  ],
  "challenges": [
    "मानसिक शंका",
    "अति-विश्लेषण",
    "चिंता",
    "गोपनीयता टकराव"
  ],
  "closing": "यह बुध गोचर मकर लग्न वालों की गहरी समझ को तेज़ करता है। विवेक से सोच परिवर्तन को सहज बनाती है।",
  "cta_context": {
    "type": "transit",
    "ascendant": "Capricorn",
    "planet": "Mercury",
    "house": 8
  }
}
