{
  "ascendant": "Leo",
  "planet": "Rahu",
  "house": 8,
  "lang": "hi",
  "title": "सिंह लग्न के लिए राहु का अष्टम भाव में गोचर",
  "summary": "राहु का अष्टम भाव में गोचर सिंह लग्न जातकों के जीवन में गहन परिवर्तन, गोपनीयता और अचानक घटनाओं को सक्रिय करता है। रहस्यमय विषयों, शोध और छिपे मामलों में रुचि बढ़ती है, जबकि साझा धन में सावधानी जरूरी है। भावनात्मक तीव्रता बढ़ती है, इसलिए नियंत्रण और पारदर्शिता आवश्यक है। सजगता से यह चरण अनिश्चितता को आंतरिक शक्ति में बदल देता है।",
  "sections": [
    {
      "heading": "मूल स्वभाव",
      "points": [
        "अज्ञात के प्रति तीव्र जिज्ञासा",
        "भीतरी भावनात्मक गहराई",
        "परिणामों पर नियंत्रण की चाह",
        "भय से सामना कर परिवर्तन"
      ]
    },
    {
      "heading": "करियर",
      "points": [
        "रिसर्च, एनालिटिक्स या जांच में सफलता",
        "पर्दे के पीछे भूमिकाएँ प्रमुख",
        "जोखिम प्रबंधन अनिवार्य",
        "अनैतिक शॉर्टकट से बचें"
      ]
    },
    {
      "heading": "रिश्ते",
      "points": [
        "भरोसे और निकटता की परीक्षा",
        "अधिकार भावना बढ़ सकती है",
        "भावनात्मक पारदर्शिता जरूरी",
        "ईमानदार संवाद से उपचार"
      ]
    },
    {
      "heading": "वित्त",
      "points": [
        "साझा धन की गहन जांच",
        "अचानक लाभ या खर्च",
        "सट्टा उधार से बचाव",
        "बीमा और अनुपालन महत्वपूर्ण"
      ]
    },
    {
      "heading": "मानसिक / आंतरिक",
      "points": [
        "गहन मनोवैज्ञानिक हलचल",
        "अनिश्चितता से चिंता",
        "आंतरिक कार्य से शक्ति",
        "छायाओं से सामना कर स्पष्टता"
      ]
    }
  ],
  "strengths": [
    "संकट सहनशक्ति",
    "गहन शोध क्षमता",
    "परिवर्तनकारी अंतर्दृष्टि",
    "रणनीतिक गोपनीयता"
  ],
  "challenges": [
    "भावनात्मक उथल-पुथल",
    "भरोसे के मुद्दे",
    "वित्तीय अस्थिरता",
    "भय-प्रेरित निर्णय"
  ],
  "closing": "यह गोचर परिवर्तन को अनिवार्य बनाता है। सजगता और अनुशासन से राहु छिपी चुनौतियों को आंतरिक शक्ति में बदल देता है।",
  "cta_context": {
    "type": "transit",
    "ascendant": "Leo",
    "planet": "Rahu",
    "house": 8
  }
}
