{
  "ascendant": "Scorpio",
  "planet": "Sun",
  "house": 2,
  "lang": "EN",
  "title": "Sun Transit in the 2nd House for Scorpio Ascendant",
  "summary": "When the Sun transits the 2nd house for Scorpio Ascendant, focus shifts to finances, values, speech, and family responsibilities. This phase highlights income visibility, authority over resources, and the need to manage wealth with discipline. Speech becomes firm and influential, but ego-driven words can create friction at home. Leadership qualities can improve financial planning if pride is kept in check. Used wisely, this transit strengthens self-worth, stabilizes earnings, and clarifies long-term value systems.",
  "sections": [
    {
      "title": "Wealth & Resources",
      "points": [
        "Greater focus on income and savings",
        "Authority over financial decisions",
        "Visibility in monetary matters",
        "Need for disciplined spending"
      ]
    },
    {
      "title": "Speech & Expression",
      "points": [
        "Firm and commanding speech",
        "Ability to influence through words",
        "Risk of harsh or ego-driven tone",
        "Importance of measured communication"
      ]
    },
    {
      "title": "Family & Values",
      "points": [
        "Responsibility toward family matters",
        "Assertion of personal values",
        "Possible dominance in family discussions",
        "Need to balance authority with respect"
      ]
    },
    {
      "title": "Career & Recognition",
      "points": [
        "Income linked to leadership roles",
        "Recognition for financial management",
        "Pressure to prove material competence",
        "Rewards for consistent effort"
      ]
    },
    {
      "title": "Mental & Inner State",
      "points": [
        "Heightened self-worth awareness",
        "Concern about financial stability",
        "Pride tied to possessions",
        "Need to align ego with values"
      ]
    }
  ],
  "strengths": [
    "Improved financial authority",
    "Influential speech",
    "Clear value system",
    "Income stability through discipline"
  ],
  "challenges": [
    "Harsh communication",
    "Ego conflicts in family",
    "Over-attachment to status",
    "Rigid financial outlook"
  ],
  "closing": "This Sun transit strengthens financial control and self-worth for Scorpio Ascendants. Progress comes from disciplined resources and respectful communication.",
  "cta_context": {
    "type": "transit",
    "ascendant": "Scorpio",
    "planet": "Sun",
    "house": 2
  }
}
