{
  "ascendant": "Capricorn",
  "planet": "Moon",
  "house": 3,
  "lang": "EN",
  "title": "Moon Transit in the 3rd House for Capricorn Ascendant",
  "summary": "When the Moon transits the 3rd house for Capricorn Ascendant, emotions connect strongly with communication, efforts, and close interactions. Curiosity increases, and you may feel mentally active, expressive, and eager to share thoughts. Short travels, writing, or conversations with siblings and peers become emotionally engaging. Mood swings can influence decision-making and communication tone. This phase supports learning and networking when emotions are managed calmly. Consistent effort and mindful speech help transform emotional impulses into productive actions.",
  "sections": [
    {
      "title": "Core Personality",
      "points": [
        "Emotion-driven communication style",
        "Increased curiosity and adaptability",
        "Strong need to express thoughts",
        "Restlessness if not mentally engaged"
      ]
    },
    {
      "title": "Career",
      "points": [
        "Favorable for communication-based tasks",
        "Good for writing, sales, or coordination",
        "Ideas flow quickly but need structure",
        "Avoid impulsive professional messages"
      ]
    },
    {
      "title": "Relationships",
      "points": [
        "Emotional exchanges with siblings highlighted",
        "Frequent conversations with peers",
        "Tone sensitivity affects interactions",
        "Listening improves mutual understanding"
      ]
    },
    {
      "title": "Finance",
      "points": [
        "Minor gains through skills or contacts",
        "Spending on travel or tools",
        "Short-term financial focus",
        "Avoid emotion-led commitments"
      ]
    },
    {
      "title": "Mental / Inner",
      "points": [
        "Mentally active and alert state",
        "Emotional restlessness possible",
        "Need for expression and movement",
        "Clarity improves with focused tasks"
      ]
    }
  ],
  "strengths": [
    "Adaptive communication",
    "Quick learning ability",
    "Emotional intelligence in dialogue",
    "Networking skills"
  ],
  "challenges": [
    "Mental restlessness",
    "Impulsive speech",
    "Mood-driven decisions",
    "Scattered focus"
  ],
  "closing": "This Moon transit energizes Capricorn Ascendants mentally and emotionally. Focused communication channels emotional energy into constructive outcomes.",
  "cta_context": {
    "type": "transit",
    "ascendant": "Capricorn",
    "planet": "Moon",
    "house": 3
  }
}
