{
  "ascendant": "Libra",
  "planet": "Mars",
  "house": 11,
  "lang": "HI",
  "title": "तुला लग्न में एकादश भाव में मंगल",
  "summary": "तुला लग्न के लिए मंगल का एकादश भाव में गोचर लक्ष्य, लाभ, नेटवर्क और प्रभाव पर तीव्रता से कार्य करवाता है। उद्देश्यों को पाने की ललक बढ़ती है और समूहों में सक्रिय भूमिका बनती है। टीम में नेतृत्व उभरता है, पर अत्यधिक प्रतिस्पर्धा से टकराव संभव है। यह समय व्यवसाय विस्तार, ऑडियंस ग्रोथ और सामूहिक प्रयासों से परिणाम देता है। जल्दबाज़ी से नुकसान हो सकता है। संतुलित सहयोग से सामाजिक ऊर्जा स्थायी सफलता में बदलती है।",
  "sections": [
    {
      "heading": "व्यक्तित्व",
      "points": [
        "लक्ष्य-केंद्रित प्रेरणा",
        "दृढ़ सामाजिक उपस्थिति",
        "परिणाम पाने की तीव्र चाह",
        "प्रतिस्पर्धी टीम दृष्टि"
      ]
    },
    {
      "heading": "करियर और दिशा",
      "points": [
        "नेटवर्क से पेशेवर वृद्धि",
        "समूह परियोजनाओं में नेतृत्व",
        "लक्ष्यों का आक्रामक पीछा",
        "सहयोगियों से प्रतिस्पर्धा न करें"
      ]
    },
    {
      "heading": "रिश्ते",
      "points": [
        "मित्रता लक्ष्य-प्रधान",
        "समूह में प्रभुत्व बढ़ सकता है",
        "प्रतिस्पर्धा से विवाद",
        "सहयोग से संबंध मजबूत"
      ]
    },
    {
      "heading": "धन और विस्तार",
      "points": [
        "नेटवर्क से आय",
        "व्यवसाय विस्तार लाभ",
        "त्वरित लाभ का दबाव",
        "दीर्घकालिक योजना आवश्यक"
      ]
    },
    {
      "heading": "स्वास्थ्य और मानसिकता",
      "points": [
        "उच्च मानसिक सक्रियता",
        "लगातार लक्ष्यों से तनाव",
        "रक्त संचार संवेदनशीलता",
        "विश्राम से संतुलन"
      ]
    }
  ],
  "strengths": [
    "लक्ष्य प्राप्ति ऊर्जा",
    "सामाजिक नेतृत्व",
    "व्यवसाय गति",
    "परिणाम उन्मुखता",
    "टीम प्रेरणा"
  ],
  "challenges": [
    "समूह टकराव",
    "लाभ की अधीरता",
    "प्रतिस्पर्धी घर्षण",
    "अधिक विस्तार",
    "तनाव संचय"
  ],
  "closing": "एकादश भाव में मंगल तुला लग्न के लाभ बढ़ाता है, जब महत्वाकांक्षा सहयोग के साथ चले।",
  "cta_context": {
    "type": "transit",
    "ascendant": "Libra",
    "planet": "Mars",
    "house": 11
  }
}
