{
  "ascendant": "Scorpio",
  "planet": "Saturn",
  "house": 11,
  "lang": "EN",
  "title": "Saturn Transit in the 11th House for Scorpio Ascendant",
  "summary": "When Saturn transits the 11th house for Scorpio Ascendant, gains, networks, and long-term goals are tested for realism and endurance. This phase brings slow but reliable progress toward ambitions through disciplined effort and selective associations. Social circles may shrink, yet the remaining connections prove dependable and purposeful. Financial gains arrive gradually, linked to sustained work rather than luck. By aligning goals with responsibility and patience, this transit delivers stable achievements and lasting fulfillment.",
  "sections": [
    {
      "title": "Core Personality",
      "points": [
        "Goals become practical and achievable",
        "Patience replaces urgency in desires",
        "Selectivity in friendships increases",
        "Satisfaction comes from steady progress"
      ]
    },
    {
      "title": "Career",
      "points": [
        "Long-term projects show steady movement",
        "Support from senior or experienced allies",
        "Team outcomes improve with structure",
        "Rewards follow consistent contribution"
      ]
    },
    {
      "title": "Relationships",
      "points": [
        "Friendships are tested for loyalty",
        "Fewer but dependable social ties remain",
        "Boundaries in groups become clear",
        "Mutual respect outweighs popularity"
      ]
    },
    {
      "title": "Finance",
      "points": [
        "Income grows gradually",
        "Gains link to sustained effort",
        "Conservative financial planning favored",
        "Avoid speculative expectations"
      ]
    },
    {
      "title": "Mental / Inner",
      "points": [
        "Detachment from unrealistic hopes",
        "Inner calm through achievable goals",
        "Motivation builds with small wins",
        "Fulfillment comes from perseverance"
      ]
    }
  ],
  "strengths": [
    "Realistic goal-setting",
    "Reliable networks",
    "Steady financial gains",
    "Enduring patience"
  ],
  "challenges": [
    "Delay in rewards",
    "Reduced social excitement",
    "Loneliness within groups",
    "Frustration with slow pace"
  ],
  "closing": "This Saturn transit teaches the value of patient ambition. Through discipline and selective alliances, it delivers durable gains and meaningful progress.",
  "cta_context": {
    "type": "transit",
    "ascendant": "Scorpio",
    "planet": "Saturn",
    "house": 11
  }
}
