{
  "ascendant": "Cancer",
  "planet": "Moon",
  "house": 7,
  "lang": "hi",
  "title": "कर्क लग्न में चंद्रमा का सप्तम भाव गोचर",
  "summary": "कर्क लग्न में चंद्रमा का सप्तम भाव गोचर साझेदारी और एक-से-एक संबंधों में भावनात्मक जागरूकता बढ़ाता है। रिश्ते केंद्र में आ जाते हैं और निकटता व आश्वासन की आवश्यकता महसूस होती है। साथी की मनोदशा के प्रति संवेदनशीलता बढ़ती है। सीमाएँ स्पष्ट न हों तो भावनात्मक निर्भरता संतुलन बिगाड़ सकती है।",
  "sections": [
    {
      "heading": "मुख्य व्यक्तित्व",
      "points": [
        "रिश्तों पर केंद्रित भावनाएँ",
        "साथ की आवश्यकता",
        "दूसरों की मनोदशा पर प्रतिक्रिया",
        "भावनात्मक संतुलन की चाह"
      ]
    },
    {
      "heading": "करियर",
      "points": [
        "क्लाइंट-फेसिंग भूमिकाएँ",
        "साझेदारी आधारित कार्य अनुकूल",
        "भावनाओं से प्रभावित बातचीत",
        "निर्णयों में वस्तुनिष्ठता रखें"
      ]
    },
    {
      "heading": "रिश्ते",
      "points": [
        "भावनात्मक जुड़ाव गहरा",
        "साथी से आश्वासन की चाह",
        "टकराव में संवेदनशीलता",
        "सीमाएँ सामंजस्य बनाए रखती हैं"
      ]
    },
    {
      "heading": "वित्त",
      "points": [
        "संयुक्त वित्तीय चर्चाएँ",
        "साथी से प्रभावित खर्च",
        "साझी जिम्मेदारियाँ",
        "स्पष्टता से भ्रम कम"
      ]
    },
    {
      "heading": "मानसिक / आंतरिक स्थिति",
      "points": [
        "दूसरों की भावनाओं का प्रतिबिंब",
        "रिश्ते की स्थिरता की चिंता",
        "आपसी समझ की चाह",
        "शांत संवाद से संतुलन"
      ]
    }
  ],
  "strengths": [
    "भावनात्मक तालमेल",
    "साझेदारी कौशल",
    "सहयोगी स्वभाव",
    "सहानुभूति"
  ],
  "challenges": [
    "भावनात्मक निर्भरता",
    "अधिक संवेदनशीलता",
    "टकराव से बचना",
    "मूड-आधारित प्रतिक्रिया"
  ],
  "closing": "यह गोचर साझेदारी में भावनात्मक संतुलन सिखाता है। सीमाओं के साथ निकटता रखें।",
  "cta_context": {
    "type": "transit_check",
    "ascendant": "Cancer",
    "planet": "Moon",
    "house": 7
  }
}
